Metadata-Version: 2.1
Name: disdat
Version: 1.1.1
Summary: Disdat: data versioning
Home-page: https://github.com/kyocum/disdat
Author: Ken Yocum
Author-email: kyocum@gmail.com
License: Apache License, version 2.0
Classifier: Development Status :: 4 - Beta
Classifier: Intended Audience :: Science/Research
Classifier: Topic :: Scientific/Engineering
Classifier: License :: OSI Approved :: Apache Software License
Classifier: Programming Language :: Python :: 3.6
Classifier: Operating System :: OS Independent
Classifier: Natural Language :: English
Requires-Python: >=3.8, <3.12
License-File: LICENSE.txt
License-File: NOTICE.txt
Requires-Dist: boto3<2.0,>=1.14.49
Requires-Dist: termcolor<2.0,>=1.1.0
Requires-Dist: pandas<3.0,>=1.5
Requires-Dist: numpy<=1.26.4,>=1.18.1
Requires-Dist: sqlalchemy<1.4,>=1.3.13
Requires-Dist: protobuf<4.0,>=3.11.2
Requires-Dist: docutils<0.16,>=0.10
Provides-Extra: dev
Requires-Dist: pytest; extra == "dev"
Requires-Dist: ipython; extra == "dev"
Requires-Dist: mock; extra == "dev"
Requires-Dist: pylint; extra == "dev"
Requires-Dist: coverage; extra == "dev"
Requires-Dist: tox; extra == "dev"
Requires-Dist: moto==2.2.13; extra == "dev"
Requires-Dist: s3fs<=0.4.2; extra == "dev"
Provides-Extra: rel
Requires-Dist: wheel; extra == "rel"
